mettagrid/__init__.py
mettagrid/base_config.py
mettagrid/demo.py
mettagrid/mettagrid_c.pyi
mettagrid/mettagrid_c.so
mettagrid/py.typed
mettagrid/types.py
mettagrid/builder/building.py
mettagrid/builder/envs.py
mettagrid/config/__init__.py
mettagrid/config/action_config.py
mettagrid/config/event_config.py
mettagrid/config/filter_config.py
mettagrid/config/game_value.py
mettagrid/config/handler_config.py
mettagrid/config/id_map.py
mettagrid/config/mettagrid_c_config.py
mettagrid/config/mettagrid_c_mutations.py
mettagrid/config/mettagrid_c_value_config.py
mettagrid/config/mettagrid_config.py
mettagrid/config/obs_config.py
mettagrid/config/reward_config.py
mettagrid/config/tag.py
mettagrid/config/vibes.py
mettagrid/config/filter/__init__.py
mettagrid/config/filter/alignment_filter.py
mettagrid/config/filter/filter.py
mettagrid/config/filter/game_value_filter.py
mettagrid/config/filter/near_filter.py
mettagrid/config/filter/resource_filter.py
mettagrid/config/filter/tag_filter.py
mettagrid/config/filter/vibe_filter.py
mettagrid/config/mutation/__init__.py
mettagrid/config/mutation/alignment_mutation.py
mettagrid/config/mutation/attack_mutation.py
mettagrid/config/mutation/clear_inventory_mutation.py
mettagrid/config/mutation/freeze_mutation.py
mettagrid/config/mutation/game_value_mutation.py
mettagrid/config/mutation/mutation.py
mettagrid/config/mutation/resource_mutation.py
mettagrid/config/mutation/stats_mutation.py
mettagrid/config/mutation/tag_mutation.py
mettagrid/envs/early_reset_handler.py
mettagrid/envs/mettagrid_puffer_env.py
mettagrid/envs/pettingzoo_env.py
mettagrid/envs/stats_tracker.py
mettagrid/map_builder/__init__.py
mettagrid/map_builder/ascii.py
mettagrid/map_builder/map_builder.py
mettagrid/map_builder/maze.py
mettagrid/map_builder/perimeter_incontext.py
mettagrid/map_builder/random_map.py
mettagrid/map_builder/utils.py
mettagrid/mapgen/area.py
mettagrid/mapgen/mapgen.py
mettagrid/mapgen/scene.py
mettagrid-0.2.0.67.dist-info/METADATA
mettagrid-0.2.0.67.dist-info/WHEEL
mettagrid-0.2.0.67.dist-info/entry_points.txt
mettagrid-0.2.0.67.dist-info/top_level.txt
mettagrid-0.2.0.67.dist-info/RECORD
mettagrid-0.2.0.67.dist-info/licenses/LICENSE
