Metadata-Version: 2.4
Name: mettagrid
Version: 0.2.0.67
Summary: A fast grid-based open-ended MARL environment
Author-email: David Bloomin <daveey@gmail.com>
License-Expression: MIT
Project-URL: Homepage, https://daveey.github.io
Project-URL: Repository, https://github.com/Metta-AI/mettagrid
Keywords: gridworld,minigrid,rl,reinforcement-learning,environment,gym
Requires-Python: <3.13,>=3.12
License-File: LICENSE
Requires-Dist: boto3>=1.38.32
Requires-Dist: botocore>=1.38.29
Requires-Dist: gymnasium>=1.1.1
Requires-Dist: importnb>=2023.11.1
Requires-Dist: pettingzoo>=1.25
Requires-Dist: pufferlib-core
Requires-Dist: pydantic>=2.12.2
Requires-Dist: pyyaml>=6.0.2
Requires-Dist: scipy-stubs>=1.17.0.0
Dynamic: license-file
